fmp4j/__init__.py
fmp4j/cli.py
fmp4j/client.py
fmp4j/version.py
fmp4j-0.2.3.dist-info/METADATA
fmp4j-0.2.3.dist-info/WHEEL
fmp4j-0.2.3.dist-info/entry_points.txt
fmp4j-0.2.3.dist-info/top_level.txt
fmp4j-0.2.3.dist-info/RECORD
